{
  "curatednews.xyz": "",
  "curatednewsbusiness.xyz": "-_-Enhanced Security Active-_-Our automated system could not get an http response but got timely headers successfully. curatednewsbusiness.xyz is either misconfigured or has active protections enabled for extra security. If you are having trouble accessing curatednewsbusiness.xyz, please make sure your browser is up-to-date, you do not have interfering browser extensions, cached data, or incorrect user-agent settings. This can indicate unusual browser behavior which may cause a page failure due to flagged security parameters.-_-Security may be permanently enabled.",
  "docs.curatednews.xyz": "-_--_--_-",
  "headlinesclassifier.curatednews.xyz": "-_--_--_-",
  "dataset.curatednews.xyz": "-_--_--_-",
  "regions.curatednews.xyz": "-_--_--_-"
}
